EasyUpdate/__init__.py
EasyUpdate/core.py
EasyUpdate/exceptions.py
easyupdate-1.0.1.dist-info/licenses/LICENSE
easyupdate-1.0.1.dist-info/METADATA
easyupdate-1.0.1.dist-info/WHEEL
easyupdate-1.0.1.dist-info/top_level.txt
easyupdate-1.0.1.dist-info/RECORD
