Metadata-Version: 2.4
Name: easyupdate
Version: 1.0.1
Summary: A lightweight Python module to automatically update your script when a new version is released. Allows compilation to `.exe` and Linux executables.
Author: GeekMan44
License: MIT License
Project-URL: Homepage, https://github.com/GeekMan44/EasyUpdate
Project-URL: Discord, https://discord.gg/Exyfg8aD3Y
Requires-Python: >=3.7
License-File: LICENSE
Requires-Dist: requests
Requires-Dist: psutil
Dynamic: license-file
